<?xml version="1.0" encoding="UTF-8"?>
<record_update table="sp_row">
    <sp_row action="INSERT_OR_UPDATE">
        <class_name/>
        <order>2</order>
        <sp_column/>
        <sp_container display_value="Cabrillo Showcase - Container 1">2c344e18dbd44f00492fd311ce9619ab</sp_container>
        <sys_class_name>sp_row</sys_class_name>
        <sys_created_by>fabio.petito</sys_created_by>
        <sys_created_on>2017-08-24 14:20:47</sys_created_on>
        <sys_customer_update>false</sys_customer_update>
        <sys_id>5c9fa51ddb7c8300f3bbd9f0ce96197e</sys_id>
        <sys_mod_count>0</sys_mod_count>
        <sys_name>2</sys_name>
        <sys_package display_value="SP Cabrillo" source="x_snc_sp_cabrillo">af524ad4dbd44f00492fd311ce9619fb</sys_package>
        <sys_policy/>
        <sys_replace_on_upgrade>false</sys_replace_on_upgrade>
        <sys_scope display_value="SP Cabrillo">af524ad4dbd44f00492fd311ce9619fb</sys_scope>
        <sys_update_name>sp_row_5c9fa51ddb7c8300f3bbd9f0ce96197e</sys_update_name>
        <sys_updated_by>fabio.petito</sys_updated_by>
        <sys_updated_on>2017-08-24 14:20:47</sys_updated_on>
    </sp_row>
</record_update>
